{"code":1,"msg":"success","data":[{"id":3558289,"title":"疏附县工业园区新型石膏建材区综合开发及配套设施建设项目（EPC+O模式）监理竞争性磋商公告","datetime":"今天","datetime_ts":1773417600000,"bid_price":"金额见正文","bid_price_yuan":0,"url":"","city":"广州","province":"","purchaser":"疏附广州工...管理委员会","types":"竞争性磋商公告","txt":"金额见正文","class":"tag-grey","created_at":"2026-03-14T13:12:46.000Z","updated_at":"2026-03-14T15:08:41.000Z"},{"id":3554128,"title":"血小板抗体检测试剂盒（固相凝集法）招标公告","datetime":"2026-03-13 11:59","datetime_ts":1773374340000,"bid_price":"¥120万元（人民币）","bid_price_yuan":1200000,"url":"http://www.ccgp.gov.cn/cggg/dfgg/gkzb/202603/t20260313_26267053.htm","city":"广州","province":"","purchaser":"广州血液中心","types":"公开招标公告","txt":"百万级","class":"tag-orange","created_at":"2026-03-13T23:09:38.000Z","updated_at":"2026-03-14T11:53:28.000Z"},{"id":3554340,"title":"广州市疾病预防控制中心（广州市卫生监督所）2026年专用卫生材料试剂耗材项目（二）（项目编号：M4400000707536008001）结果公告","datetime":"2026-03-13 11:20","datetime_ts":1773372000000,"bid_price":"金额见正文","bid_price_yuan":0,"url":"","city":"广州","province":"","purchaser":"广州市疾病预防控制中心（广州市卫生监督所）","types":"中标公告","txt":"金额见正文","class":"tag-grey","created_at":"2026-03-13T23:09:38.000Z","updated_at":"2026-03-14T11:53:28.000Z"},{"id":3557544,"title":"2026年广州市黄埔区农贸市场、大型超市、生鲜电商及门店食用农产品快速检测技术服务及广东省食用农产品市场销售安全监管系统推广服务项目(二次)竞争性磋商公告","datetime":"昨天","datetime_ts":1773331200000,"bid_price":"金额见正文","bid_price_yuan":0,"url":"","city":"广州","province":"","purchaser":"广州市黄埔...监督管理局","types":"竞争性磋商公告","txt":"金额见正文","class":"tag-grey","created_at":"2026-03-14T04:22:45.000Z","updated_at":"2026-03-14T15:08:41.000Z"},{"id":3556921,"title":"广州市花都区民政局2026年度民政系统安保服务带量集中采购项目（CZ2026-0216）采购更正公告（第一次）","datetime":"昨天","datetime_ts":1773331200000,"bid_price":"金额见正文","bid_price_yuan":0,"url":"","city":"广州","province":"","purchaser":"广州市花都区民政局","types":"更正公告","txt":"金额见正文","class":"tag-grey","created_at":"2026-03-13T12:54:47.000Z","updated_at":"2026-03-14T15:08:41.000Z"},{"id":3556909,"title":"建设工程消防验收服务招标公告","datetime":"昨天","datetime_ts":1773331200000,"bid_price":"¥196万元（人民币）","bid_price_yuan":1960000,"url":"","city":"广州","province":"","purchaser":"广州开发区...安全监督站","types":"公开招标公告","txt":"百万级","class":"tag-orange","created_at":"2026-03-13T12:54:47.000Z","updated_at":"2026-03-14T15:08:41.000Z"},{"id":3556687,"title":"2026年海珠区事业单位公开招聘考务服务项目招标公告","datetime":"昨天","datetime_ts":1773331200000,"bid_price":"¥248万元（人民币）","bid_price_yuan":2480000,"url":"","city":"广州","province":"","purchaser":"广州市海珠...社会保障局","types":"公开招标公告","txt":"百万级","class":"tag-orange","created_at":"2026-03-13T13:30:01.000Z","updated_at":"2026-03-14T15:08:41.000Z"},{"id":3556521,"title":"广州市疾病预防控制中心（广州市卫生监督所）2026年专用卫生材料试剂耗材项目（一）（项目编号：M4400000707536007）结果公告附件","datetime":"昨天","datetime_ts":1773331200000,"bid_price":"金额见正文","bid_price_yuan":0,"url":"","city":"广州","province":"","purchaser":"广州市疾病...生监督所）","types":"更正公告","txt":"金额见正文","class":"tag-grey","created_at":"2026-03-13T12:05:06.000Z","updated_at":"2026-03-14T15:08:41.000Z"},{"id":3556516,"title":"广州市疾病预防控制中心（广州市卫生监督所）2026年专用卫生材料试剂耗材项目（二）（项目编号：M4400000707536008001）结果公告附件","datetime":"昨天","datetime_ts":1773331200000,"bid_price":"金额见正文","bid_price_yuan":0,"url":"","city":"广州","province":"","purchaser":"广州市疾病...生监督所）","types":"更正公告","txt":"金额见正文","class":"tag-grey","created_at":"2026-03-13T12:05:06.000Z","updated_at":"2026-03-14T15:08:41.000Z"},{"id":3556511,"title":"广州市地质灾害自动化监测预警网络扩面提质项目(一期)——地质灾害风险区自动化监测台站建设（一期）监理服务（CZ2026-0108）招标公告","datetime":"昨天","datetime_ts":1773331200000,"bid_price":"¥29.01万元（人民币）","bid_price_yuan":290100,"url":"","city":"广州","province":"","purchaser":"广州市地质...促进中心)","types":"公开招标公告","txt":"十万级","class":"tag-blue","created_at":"2026-03-13T12:05:06.000Z","updated_at":"2026-03-14T15:08:41.000Z"}],"total":340,"syncMeta":{"actionAt":1773500844239,"successAt":1773500696588},"statsMeta":null,"generatedAt":1773500986722,"cacheScope":{"type":"city","value":"广州","page":0,"pageSize":10}}